{
  "config": {
    "horizon": 2,
    "steps": 2,
    "random_seed": 0,
    "mode": "state_inference",
    "policy_len": 2,
    "tmaze": {
      "num_states": 2,
      "num_obs": 2,
      "num_actions": 2,
      "likelihood_diag": 0.9,
      "preference_goal": 2.0
    },
    "agent": {
      "inference_algo": "fpi",
      "action_selection": "deterministic"
    },
    "logging": {
      "enabled": true,
      "path": "output/logs/pymdp_runs.jsonl"
    },
    "comparison": {
      "horizons": [
        2,
        3
      ],
      "seeds": [
        0
      ],
      "modes": [
        "state_inference",
        "policy_inference"
      ]
    }
  },
  "config_hash": "81eb061f43b7bfd7",
  "mode": "state_inference",
  "seed": 0,
  "policy_len": 2,
  "steps": 2,
  "log_path": "output/logs/pymdp_runs.jsonl",
  "log_record_count": 3,
  "goal_reached": true
}